pypi_test_002/__init__.py
pypi_test_002/config.py
pypi_test_002/main.py
pypi_test_002-0.1.0.dist-info/LICENSE
pypi_test_002-0.1.0.dist-info/METADATA
pypi_test_002-0.1.0.dist-info/WHEEL
pypi_test_002-0.1.0.dist-info/entry_points.txt
pypi_test_002-0.1.0.dist-info/top_level.txt
pypi_test_002-0.1.0.dist-info/RECORD
