Metadata-Version: 2.1
Name: pypi_test_002
Version: 0.1.0
Summary: Description of the pypi_test_002 package. 
Author: wukunhuan
Author-email: wukunhuan1208@163.com
Classifier: Programming Language :: Python :: 3
Classifier: License :: OSI Approved :: MIT License
Classifier: Operating System :: OS Independent
Requires-Python: >=3.8
License-File: LICENSE
Requires-Dist: argparse
